kiwistron_ipconfig/__init__.py
kiwistron_ipconfig/_version.py
kiwistron_ipconfig/core.py
kiwistron_ipconfig/gui.py
kiwistron_ipconfig-0.1.0.dist-info/licenses/LICENSE.txt
kiwistron_ipconfig-0.1.0.dist-info/METADATA
kiwistron_ipconfig-0.1.0.dist-info/WHEEL
kiwistron_ipconfig-0.1.0.dist-info/top_level.txt
kiwistron_ipconfig-0.1.0.dist-info/RECORD
