Metadata-Version: 2.4
Name: kiwistron_ipconfig
Version: 0.1.0
Summary: Serial-based network scanner and lightweight GUI to configure device Wi-Fi and get stream URL (Kiwistron IP config).
Author-email: Your Name <you@example.com>
License: MIT
Project-URL: Homepage, https://example.com/kiwistron_ipconfig
Keywords: esp32,serial,tkinter,camera,network,ipconfig,kiwistron
Requires-Python: >=3.8
License-File: LICENSE.txt
Dynamic: license-file
